fastlife/__init__.py
fastlife/__main__.py
fastlife/exceptions.py
fastlife/grid.py
fastlife/sequential.py
fastlife/utils.py
fastlife/version.py
fastlife-0.2.dist-info/LICENSE
fastlife-0.2.dist-info/METADATA
fastlife-0.2.dist-info/WHEEL
fastlife-0.2.dist-info/entry_points.txt
fastlife-0.2.dist-info/top_level.txt
fastlife-0.2.dist-info/RECORD
