Metadata-Version: 2.1
Name: fastlife
Version: 0.2
Summary: Benchmarks for implementations of Conway's Game of Life
Home-page: https://fastlife.readthedocs.io/en/latest/
Author: Benjamin Bengfort
Author-email: benjamin@bengfort.com
License: BSD 3-Clause
Download-URL: https://github.com/bbengfort/fastlife/tarball/v0.2
Project-URL: Documentation, https://fastlife.readthedocs.io/en/latest/
Project-URL: Download, https://github.com/bbengfort/fastlife/tarball/v0.2
Project-URL: Source, https://github.com/bbengfort/fastlife
Project-URL: Tracker, https://github.com/bbengfort/fastlife/issues
Keywords: cython,game of life,cellular automata,parallel processing,benchmarks
Platform: UNKNOWN
Classifier: Development Status :: 2 - Pre-Alpha
Classifier: Intended Audience :: Developers
Classifier: Intended Audience :: Science/Research
Classifier: License :: OSI Approved :: BSD License
Classifier: Natural Language :: English
Classifier: Operating System :: OS Independent
Classifier: Programming Language :: Python
Classifier: Programming Language :: Python :: 3.5
Classifier: Programming Language :: Python :: 3.6
Classifier: Programming Language :: Python :: 3.7
Classifier: Programming Language :: Python :: 3.8
Classifier: Topic :: Scientific/Engineering :: Artificial Life
Classifier: Topic :: Software Development
Classifier: Topic :: Software Development :: Libraries :: Python Modules
Requires-Python: >=3.4, <4
Requires-Dist: numpy (==1.19.1)
Requires-Dist: matplotlib (==3.3.0)
Requires-Dist: memory-profiler (==0.57.0)
Requires-Dist: tqdm (==4.48.0)
